<wongilla>
    <scene name="platformerScene" controller="PlatformerController">

        <pixmap name="level1" path="images/newlevels.png"/>
        <texture name="kennyTexture" path="images/spritesheet.png"/>
        <tileset name="kennyTileSet" src="kennyTexture" margin="2" cellspacing="2" col="30" row="30" tile-width="21"
                 tile-height="21"/>


        <TiledMapRender name="gameMap" file="images/test.tmx" display-width="32" display-height="32">
        </TiledMapRender>

        <ControllerLayer/>

        <animator name="kenny" x="101" y="224" tile-set="kennyTileSet" play="walk" display-width="32"
                  display-height="32">
            <animation name="walk" indexes="[29,0],[28,0]" duration="0.5"/>
        </animator>

        <table name="mapTable" debug="all">
            <tr expand="true">
                <td align="right" valign="top">

                    <table>
                        <tr>
                            <td>
                                <checkbox value="IsGrounded">Grounded</checkbox>
                            </td>
                        </tr>
                        <tr>
                            <td>
                                <checkbox value="IsGravity">Gravity</checkbox>
                            </td>
                        </tr>
                        <tr>
                            <td>
                                <textfield value="MAX_DISTANCE" numeric="true"></textfield>
                            </td>
                        </tr>
                    </table>

                </td>
            </tr>
            <tr expand="true">
                <td align="left" valign="bottom">
                    <touchpad name="touchpad" visible="false"></touchpad>
                </td>
            </tr>
        </table>

        <textbutton x="91" y="70" OnClickTo="index.xml">Back to Start Menu</textbutton>
        <textbutton x="291" y="70" OnClickTo="resetEntity()">Reset Entity</textbutton>
        <textbutton x="391" y="70" OnClickTo="enableGravity()">Gravity</textbutton>

        <label name="info" x="0" y="0">Info</label>
        <label name="mapInfo" x="300" y="0">Info</label>


    </scene>
</wongilla>